py_replay_bg/__init__.py
py_replay_bg/py_replay_bg.py
py_replay_bg/analyzer/__init__.py
py_replay_bg/data/__init__.py
py_replay_bg/dss/__init__.py
py_replay_bg/dss/default_dss_handlers.py
py_replay_bg/environment/__init__.py
py_replay_bg/example/code/analysis_example.py
py_replay_bg/example/code/analysis_intervals_example.py
py_replay_bg/example/code/fake_CGM.py
py_replay_bg/example/code/get_started.py
py_replay_bg/example/code/replay_intervals_map.py
py_replay_bg/example/code/replay_intervals_mcmc.py
py_replay_bg/example/code/replay_map.py
py_replay_bg/example/code/replay_map_dss.py
py_replay_bg/example/code/replay_map_fakecgm.py
py_replay_bg/example/code/replay_mcmc.py
py_replay_bg/example/code/replay_mcmc_dss.py
py_replay_bg/example/code/twin_intervals_map.py
py_replay_bg/example/code/twin_intervals_mcmc.py
py_replay_bg/example/code/twin_map.py
py_replay_bg/example/code/twin_map_extended.py
py_replay_bg/example/code/twin_mcmc.py
py_replay_bg/example/code/twin_mcmc_extended.py
py_replay_bg/example/code/utils.py
py_replay_bg/input_validation/__init__.py
py_replay_bg/input_validation/input_validator_init.py
py_replay_bg/input_validation/input_validator_replay.py
py_replay_bg/input_validation/input_validator_twin.py
py_replay_bg/model/__init__.py
py_replay_bg/model/logpriors_t1d.py
py_replay_bg/model/model_parameters_t1d.py
py_replay_bg/model/model_step_equations_t1d.py
py_replay_bg/model/model_step_equations_t1d_torch.py
py_replay_bg/model/t1d_model_multi_meal.py
py_replay_bg/model/t1d_model_single_meal.py
py_replay_bg/replay/__init__.py
py_replay_bg/sensors/CGM.py
py_replay_bg/sensors/Vettoretti19CGM.py
py_replay_bg/sensors/__init__.py
py_replay_bg/tests/__init__.py
py_replay_bg/tests/test_analysis_example.py
py_replay_bg/tests/test_analysis_intervals_example.py
py_replay_bg/tests/test_replay_intervals_map.py
py_replay_bg/tests/test_replay_intervals_mcmc.py
py_replay_bg/tests/test_replay_map.py
py_replay_bg/tests/test_replay_map_dss.py
py_replay_bg-1.2.1.dist-info/METADATA
py_replay_bg-1.2.1.dist-info/WHEEL
py_replay_bg-1.2.1.dist-info/top_level.txt
py_replay_bg-1.2.1.dist-info/RECORD
