Metadata-Version: 2.4
Name: py_replay_bg
Version: 1.2.1
Summary: ReplayBG is a digital twin-based methodology to assess new strategies for type 1 diabetes management.
Author-email: Giacomo Cappon <cappongiacomo@gmail.com>
License: GPL-3.0-or-later
Project-URL: Homepage, https://github.com/gcappon/py_replay_bg
Project-URL: Bug Tracker, https://github.com/gcappon/py_replay_bg/issues
Classifier: Programming Language :: Python :: 3
Classifier: License :: OSI Approved :: GNU General Public License v3 (GPLv3)
Classifier: Operating System :: OS Independent
Classifier: Intended Audience :: Science/Research
Classifier: Topic :: Scientific/Engineering
Requires-Python: >=3.11
Requires-Dist: build==1.2.1
Requires-Dist: celerite==0.4.2
Requires-Dist: certifi==2024.2.2
Requires-Dist: charset-normalizer==3.3.2
Requires-Dist: contourpy==1.2.0
Requires-Dist: corner==2.2.2
Requires-Dist: coverage==7.4.4
Requires-Dist: cycler==0.12.1
Requires-Dist: docutils==0.20.1
Requires-Dist: emcee==3.1.4
Requires-Dist: et-xmlfile==1.1.0
Requires-Dist: fonttools==4.50.0
Requires-Dist: idna==3.6
Requires-Dist: importlib_metadata==7.1.0
Requires-Dist: iniconfig==2.0.0
Requires-Dist: jaraco.classes==3.3.1
Requires-Dist: jaraco.context==4.3.0
Requires-Dist: jaraco.functools==4.0.0
Requires-Dist: joblib==1.3.2
Requires-Dist: keyring==25.0.0
Requires-Dist: kiwisolver==1.4.5
Requires-Dist: llvmlite==0.42.0
Requires-Dist: markdown-it-py==3.0.0
Requires-Dist: matplotlib==3.8.3
Requires-Dist: mdurl==0.1.2
Requires-Dist: more-itertools==10.2.0
Requires-Dist: mpi4py==3.1.5
Requires-Dist: nh3==0.2.17
Requires-Dist: numba==0.59.1
Requires-Dist: numpy==1.26.4
Requires-Dist: openpyxl==3.1.2
Requires-Dist: packaging==24.0
Requires-Dist: pandas==2.2.1
Requires-Dist: patsy==0.5.6
Requires-Dist: pillow==10.2.0
Requires-Dist: pkginfo==1.10.0
Requires-Dist: plotly==5.20.0
Requires-Dist: pluggy==1.4.0
Requires-Dist: py-agata==0.0.8
Requires-Dist: Pygments==2.17.2
Requires-Dist: pyparsing==3.1.2
Requires-Dist: pyproject_hooks==1.0.0
Requires-Dist: pytest==8.1.1
Requires-Dist: pytest-cov==5.0.0
Requires-Dist: python-dateutil==2.9.0.post0
Requires-Dist: pytz==2024.1
Requires-Dist: readme_renderer==43.0
Requires-Dist: requests==2.31.0
Requires-Dist: requests-toolbelt==1.0.0
Requires-Dist: rfc3986==2.0.0
Requires-Dist: rich==13.7.1
Requires-Dist: scikit-learn==1.4.1.post1
Requires-Dist: scipy==1.12.0
Requires-Dist: seaborn==0.13.2
Requires-Dist: six==1.16.0
Requires-Dist: statsmodels==0.14.1
Requires-Dist: tenacity==8.2.3
Requires-Dist: threadpoolctl==3.4.0
Requires-Dist: tqdm==4.66.2
Requires-Dist: twine==5.0.0
Requires-Dist: tzdata==2024.1
Requires-Dist: urllib3==2.2.1
Requires-Dist: zipp==3.18.1
